yuclid/__init__.py
yuclid/cli.py
yuclid/log.py
yuclid/plot.py
yuclid/run.py
yuclid/spread.py
yuclid-0.1.12.dist-info/METADATA
yuclid-0.1.12.dist-info/WHEEL
yuclid-0.1.12.dist-info/entry_points.txt
yuclid-0.1.12.dist-info/top_level.txt
yuclid-0.1.12.dist-info/RECORD
