Metadata-Version: 2.4
Name: yuclid
Version: 0.1.12
Summary: Run experiments and interactively plot results across combinations of user-specified dimensions
Author-email: Federico Sossai <federico.sossai@gmail.com>
Project-URL: Homepage, https://github.com/fsossai/yuclid
Requires-Python: >=3.8
Requires-Dist: pandas
Requires-Dist: numpy
Requires-Dist: matplotlib
Requires-Dist: seaborn
Requires-Dist: scipy
